{"connections": [{"content_name": "Msg1", "producer_process_component": "C1", "producer_process_name": "node_11", "consumer_process_name": "node_12", "content_type": "ROSMSG", "consumer_process_component": "C1"}, {"content_name": "Msg1", "producer_process_component": "C2", "producer_process_name": "node_21", "consumer_process_name": "node_22", "content_type": "ROSMSG", "consumer_process_component": "C2"}, {"content_name": "Msg1", "producer_process_component": "C3", "producer_process_name": "node_31", "consumer_process_name": "node_32", "content_type": "ROSMSG", "consumer_process_component": "C3"}, {"content_name": "Msg1", "producer_process_component": "C3", "producer_process_name": "node_31", "consumer_process_name": "node_22", "content_type": "ROSMSG", "consumer_process_component": "C2"}, {"content_name": "Msg1", "producer_process_component": "C3", "producer_process_name": "node_31", "consumer_process_name": "node_11", "content_type": "ROSMSG", "consumer_process_component": "C1"}, {"content_name": "Msg1", "producer_process_component": "C2", "producer_process_name": "node_22", "consumer_process_name": "node_11", "content_type": "ROSMSG", "consumer_process_component": "C1"}, {"content_name": "Msg1", "producer_process_component": "C1", "producer_process_name": "node_12", "consumer_process_name": "node_22", "content_type": "ROSMSG", "consumer_process_component": "C2"}, {"content_name": "Msg1", "producer_process_component": "C3", "producer_process_name": "node_31", "consumer_process_name": "node_12", "content_type": "ROSMSG", "consumer_process_component": "C1"}]}